purplship/mappers/purolator_courier/__init__.py
purplship/mappers/purolator_courier/mapper.py
purplship/mappers/purolator_courier/proxy.py
purplship/mappers/purolator_courier/settings.py
purplship/providers/purolator_courier/__init__.py
purplship/providers/purolator_courier/address.py
purplship/providers/purolator_courier/error.py
purplship/providers/purolator_courier/pickup/__init__.py
purplship/providers/purolator_courier/pickup/cancel.py
purplship/providers/purolator_courier/pickup/create.py
purplship/providers/purolator_courier/pickup/update.py
purplship/providers/purolator_courier/pickup/validate.py
purplship/providers/purolator_courier/rate.py
purplship/providers/purolator_courier/shipment/__init__.py
purplship/providers/purolator_courier/shipment/cancel.py
purplship/providers/purolator_courier/shipment/create.py
purplship/providers/purolator_courier/shipment/documents.py
purplship/providers/purolator_courier/tracking.py
purplship/providers/purolator_courier/units.py
purplship/providers/purolator_courier/utils.py
purplship.purolator_courier-2021.5.dist-info/WHEEL
purplship.purolator_courier-2021.5.dist-info/METADATA
purplship.purolator_courier-2021.5.dist-info/RECORD
