Metadata-Version: 2.1
Name: purplship.purolator-courier
Version: 2021.5
Summary: Purplship - Purolator Courier Shipping Extension
Home-page: https://sdk.purplship.com
License: LGPLv3
Author: Dan Kobina
Author-email: danielkobina@gmail.com
Requires-Python: >=3.7,<4.0
Classifier: Intended Audience :: Developers
Classifier: License :: OSI Approved :: GNU Lesser General Public License v3 (LGPLv3)
Classifier: License :: Other/Proprietary License
Classifier: Operating System :: OS Independent
Classifier: Programming Language :: Python :: 3
Classifier: Programming Language :: Python :: 3.7
Classifier: Programming Language :: Python :: 3.8
Classifier: Programming Language :: Python :: 3.9
Requires-Dist: carrier.purolator (>=2020.4.1,<2021.0.0)
Requires-Dist: purplship (>=2021.2.2,<2022.0.0)
Project-URL: Repository, https://github.com/Purplship/purplship
